Metadata-Version: 2.1
Name: nambazasimu
Version: 0.1.0
Summary: A package to identify Tanzanian phone number carriers.
Home-page: https://github.com/genie360s/nambazasimu
Author: Alex Mkwizu
Author-email: alexgmkwizu@gmail.com
Classifier: Programming Language :: Python :: 3
Classifier: License :: OSI Approved :: MIT License
Classifier: Operating System :: OS Independent
Requires-Python: >=3.6
License-File: LICENSE
